adatoolbox/__init__.py
adatoolbox/domain/auth/__init__.py
adatoolbox/domain/auth/base_authentication.py
adatoolbox/domain/auth/exception_handler.py
adatoolbox/domain/auth/settings.py
adatoolbox/domain/database/__init__.py
adatoolbox/domain/database/base_model.py
adatoolbox/domain/database/settings.py
adatoolbox/domain/event/__init__.py
adatoolbox/domain/event/adapters/__init__.py
adatoolbox/domain/event/adapters/mq_publisher_adapter.py
adatoolbox/domain/event/adapters/pika_adapter.py
adatoolbox/domain/memory/__init__.py
adatoolbox/domain/memory/memory.py
adatoolbox/domain/secret/__init__.py
adatoolbox/domain/secret/doppler.py
adatoolbox/domain/secret/settings.py
adatoolbox/utils/enum.py
adatoolbox-0.4.16.dist-info/LICENSE
adatoolbox-0.4.16.dist-info/METADATA
adatoolbox-0.4.16.dist-info/WHEEL
adatoolbox-0.4.16.dist-info/top_level.txt
adatoolbox-0.4.16.dist-info/RECORD
