Metadata-Version: 2.1
Name: adatoolbox
Version: 0.4.16
Summary: adatoolbox
Author-email: Lojas Engecon <tecnologia@lojasengecon.com.br>
Project-URL: Bug Tracker, https://github.com/pievotecnologia/adatoolbox
Project-URL: Homepage, https://github.com/pievotecnologia/adatoolbox
Classifier: Programming Language :: Python :: 3
Classifier: License :: OSI Approved :: MIT License
Classifier: Operating System :: OS Independent
Requires-Python: >=3.7
License-File: LICENSE
